{
	"name": "Flattown",
	"colors": {
		"editor.background": "#1d1f21",
		"editor.foreground": "#c5c8c6",
		"activityBarBadge.background": "#282a2e",
		"sideBarTitle.foreground": "#bbbbbb"
	},
	"tokenColors": [
		{
			"scope": [
				"comment",
				"string.quoted.docstring",
				"punctuation.definition.comment"
			],
			"settings": {
				"foreground": "#60666b",
			}
		},
		{
			"scope": [
				"constant",
				"support.constant"
			],
			"settings": {
				"foreground": "#5ea770",
			}
		},
		{
			"scope": "string",
			"settings": {
				"foreground": "#abd977",
			}
		},
		{
			"scope": "entity.name.function",
			"settings": {
				"foreground": "#af87d7",
			}
		},
		{
			"scope": "entity.name.function.decorator",
			"settings": {
				"foreground": "#cf4f3e",
			}
		},
		{
			"scope": "entity.other.attribute-name",
			"settings": {
				"foreground": "#9ac1d8",
			}
		},
		{
			"scope": [
				"entity.name.type",
				"entity.other.inherited-class"
			],
			"settings": {
				"foreground": "#4276df",
			}
		},
		{
			"scope": "entity.name.tag",
			"settings": {
				"foreground": "#cf4f3e",
			}
		},
		{
			"scope": "storage",
			"settings": {
				"foreground": "#cf4f3e",
			}
		},
		{
			"scope": "keyword",
			"settings": {
				"foreground": "#ec9751",
			}
		},
		{
			"scope": [
				"keyword.control.import",
				"keyword.other.special-method",
				"keyword.codetag"
			],
			"settings": {
				"foreground": "#cf4f3e",
			}
		},
		{
			"scope": [
				"keyword.operator",
				"punctuation.separator",
				"punctuation.terminator",
				"punctuation.definition",
				"punctuation.section",
				"punctuation.attribute-shorthand"
			],
			"settings": {
				"foreground": "#FFD75F",
			}
		},
		{
			"scope": "variable",
			"settings": {
				"foreground": "#9ac1d8",
			}
		},
		{
			"scope": "support.function",
			"settings": {
				"foreground": "#af87d7",
			}
		},
		{
			"scope": "support.function.builtin",
			"settings": {
				"foreground": "#cf4f3e",
			}
		},
		{
			"scope": "support.class",
			"settings": {
				"foreground": "#4276df",
			}
		},
		{
			"scope": "support.type",
			"settings": {
				"foreground": "#9ac1d8",
			}
		},
		{
			"name": "Markdown - Markup Raw Inline",
			"scope": [
				"text.html.markdown markup.inline.raw.markdown"
			],
			"settings": {
				"foreground": "#C792EA"
			}
		},
		{
			"name": "Markdown - Markup Raw Inline Punctuation",
			"scope": [
				"text.html.markdown markup.inline.raw.markdown punctuation.definition.raw.markdown"
			],
			"settings": {
				"foreground": "#65737E"
			}
		},
		{
			"name": "Markdown - Heading",
			"scope": [
				"markup.heading"
			],
			"settings": {
				"fontStyle": "bold",
				"foreground": "#FFFFFF"
			}
		},
		{
			"name": "Markup - Italic",
			"scope": [
				"markup.italic"
			],
			"settings": {
				"fontStyle": "italic",
				"foreground": "#FFFFFF"
			}
		},
		{
			"name": "Markup - Bold",
			"scope": [
				"markup.bold",
				"markup.bold string"
			],
			"settings": {
				"fontStyle": "bold",
				"foreground": "#FFFFFF"
			}
		},
		{
			"name": "Markup - Bold-Italic",
			"scope": [
				"markup.bold markup.italic",
				"markup.italic markup.bold",
				"markup.quote markup.bold",
				"markup.bold markup.italic string",
				"markup.italic markup.bold string",
				"markup.quote markup.bold string"
			],
			"settings": {
				"fontStyle": "bold",
				"foreground": "#FFFFFF"
			}
		},
		{
			"name": "Markup - Underline",
			"scope": [
				"markup.underline"
			],
			"settings": {
				"fontStyle": "underline",
				"foreground": "#F78C6C"
			}
		},
		{
			"name": "Markdown - Blockquote",
			"scope": [
				"markup.quote punctuation.definition.blockquote.markdown"
			],
			"settings": {
				"foreground": "#65737E"
			}
		},
		{
			"name": "Markup - Quote",
			"scope": [
				"markup.quote"
			],
			"settings": {
				"fontStyle": "italic"
			}
		},
		{
			"name": "Markdown - Link",
			"scope": [
				"string.other.link.title.markdown"
			],
			"settings": {
				"foreground": "#82AAFF"
			}
		},
		{
			"name": "Markdown - Link Description",
			"scope": [
				"string.other.link.description.title.markdown"
			],
			"settings": {
				"foreground": "#C792EA"
			}
		},
		{
			"name": "Markdown - Link Anchor",
			"scope": [
				"constant.other.reference.link.markdown"
			],
			"settings": {
				"foreground": "#FFCB6B"
			}
		},
		{
			"name": "Markup - Raw Block",
			"scope": [
				"markup.raw.block"
			],
			"settings": {
				"foreground": "#78af8d"
			}
		},
		{
			"name": "Markdown - Raw Block Fenced",
			"scope": [
				"markup.raw.block.fenced.markdown"
			],
			"settings": {
				"foreground": "#00000050"
			}
		},
		{
			"name": "Markdown - Fenced Bode Block",
			"scope": [
				"punctuation.definition.fenced.markdown"
			],
			"settings": {
				"foreground": "#00000050"
			}
		},
		{
			"name": "Markdown - Fenced Bode Block Variable",
			"scope": [
				"markup.raw.block.fenced.markdown",
				"variable.language.fenced.markdown",
				"punctuation.section.class.end"
			],
			"settings": {
				"foreground": "#EEFFFF"
			}
		},
		{
			"name": "Markdown - Fenced Language",
			"scope": [
				"variable.language.fenced.markdown"
			],
			"settings": {
				"foreground": "#65737E"
			}
		},
		{
			"name": "Markdown - Separator",
			"scope": [
				"meta.separator"
			],
			"settings": {
				"fontStyle": "bold",
				"foreground": "#65737E"
			}
		},
		{
			"name": "Markup - Table",
			"scope": [
				"markup.table"
			],
			"settings": {
				"foreground": "#EEFFFF"
			}
		}
	]
}
